py_diffbro/__init__.py
py_diffbro/main.py
py_diffbro/modules/app_types.py
py_diffbro/modules/bro.py
py_diffbro/modules/cmd.py
py_diffbro/modules/constants.py
py_diffbro/modules/git.py
py_diffbro/modules/llm.py
diffbro-1.0.2.dist-info/METADATA
diffbro-1.0.2.dist-info/WHEEL
diffbro-1.0.2.dist-info/entry_points.txt
diffbro-1.0.2.dist-info/RECORD
