Metadata-Version: 2.1
Name: diffbro
Version: 1.0.2
Summary: Your personal AI assistant bro for better code reviews.
Home-page: https://github.com/disler/diffbro.git
License: MIT
Author: IndyDevDan
Author-email: minor7addfloortom@gmail.com
Requires-Python: >=3.8,<4.0
Classifier: License :: OSI Approved :: MIT License
Classifier: Programming Language :: Python :: 3
Classifier: Programming Language :: Python :: 3.8
Classifier: Programming Language :: Python :: 3.9
Classifier: Programming Language :: Python :: 3.10
Classifier: Programming Language :: Python :: 3.11
Requires-Dist: openai (>=0.27.8,<0.28.0)
Requires-Dist: pydantic (>=2.1.1,<3.0.0)
Requires-Dist: python-dotenv (>=1.0.0,<2.0.0)
Project-URL: Repository, https://github.com/disler/diffbro.git
